<?xml version="1.0" encoding="utf-8" ?>
<Defs>
	<!-- Dryad? privates -->
	<rjw.HediffDef_SexPart ParentName="NaturalPrivatePartPenis">
		<defName>ResinPenis</defName>
		<label>resin protrusion</label>
		<labelNoun>a resin protrusion</labelNoun>
		<description>Hardened mass of resin, its hard enough.</description>
		<descriptionHyperlinks>
			<ThingDef>ResinGlob</ThingDef>
		</descriptionHyperlinks>
		<fluid>Resin</fluid>
		<partTags>
			<li>Rigid</li>
			<li>STDImmune</li>
		</partTags>
	</rjw.HediffDef_SexPart>

	<rjw.HediffDef_SexPart ParentName="NaturalPrivatePartVagina">
		<defName>ResinVagina</defName>
		<label>resin hole</label>
		<labelNoun>a resin hole</labelNoun>
		<description>A slick hole covered with viscous organic liquids.</description>
		<descriptionHyperlinks><ThingDef>ResinGlob</ThingDef></descriptionHyperlinks>
		<spawnThingOnRemoved>ResinGlob</spawnThingOnRemoved>
		<fluid>Resin</fluid>
		<partTags>
			<li>Rigid</li>
			<li>Loose</li>
			<li>STDImmune</li>
		</partTags>
	</rjw.HediffDef_SexPart>

	<rjw.HediffDef_SexPart ParentName="NaturalPrivatePartAnus">
		<defName>ResinAnus</defName>
		<label>resin hole</label>
		<labelNoun>a resin hole</labelNoun>
		<description>A slick hole covered with viscous organic liquids.</description>
		<descriptionHyperlinks><ThingDef>ResinGlob</ThingDef></descriptionHyperlinks>
		<spawnThingOnRemoved>ResinGlob</spawnThingOnRemoved>
		<fluid>Resin</fluid>
		<partTags>
			<li>Rigid</li>
			<li>Loose</li>
			<li>STDImmune</li>
		</partTags>
	</rjw.HediffDef_SexPart>

	<rjw.HediffDef_SexPart ParentName="NaturalPrivatePartBreast">
		<defName>ResinBreasts</defName>
		<label>resin blobs</label>
		<labelNoun>a pair of resin blobs</labelNoun>
		<fluid>Resin</fluid>
		<description>A pair resin blobs filled with viscous organic liquids.</description>
		<descriptionHyperlinks><ThingDef>ResinGlob</ThingDef></descriptionHyperlinks>
		<spawnThingOnRemoved>ResinGlob</spawnThingOnRemoved>
		<partTags>
			<li>STDImmune</li>
		</partTags>
	</rjw.HediffDef_SexPart>
</Defs>