<?xml version="1.0" encoding="utf-8" ?>

<Defs>
	<InteractionDef ParentName="RJW_InteractionDefBaseSex">
		<defName>Sex_Reverse_Rimming</defName>
		<label>rimming</label>
		<logRulesInitiator>
			<rulesStrings>
				<li>r_logentry->Rimmed [RECIPIENT_nameDef].</li>
			</rulesStrings>
		</logRulesInitiator>
		<logRulesRecipient>
			<rulesStrings>
				<li>r_logentry->Was rimmed by [INITIATOR_nameDef].</li>
			</rulesStrings>
		</logRulesRecipient>
		<modExtensions>
			<li Class="rjw.InteractionExtension">
				<RMBLabel>Give anal rimming</RMBLabel>
				<rjwSextype>Rimming</rjwSextype>
				<rulepack_defs>
					<li>RimmingReverseRP</li>
				</rulepack_defs>
			</li>
			<li Class="rjw.Modules.Interactions.DefModExtensions.InteractionSelectorExtension">
				<tags>
					<li>Reverse</li>
					<li>Whoring</li>
					<li>Consensual</li>
				</tags>
				<dominantRequirement>
					<tongue>true</tongue>
				</dominantRequirement>
				<submissiveRequirement>
					<families>
						<li>Anus</li>
					</families>
				</submissiveRequirement>
			</li>
		</modExtensions>
	</InteractionDef>
</Defs>